Workbook

Sheet Segment Summary
A1: Digital Product System - 12 Segments, 217 Product Ideas
A2: Every number below is a formula that reads from the 'Product Ideas' and 'Assumptions' sheets.
A4: # | B4: Segment | C4: No. of Ideas | D4: Avg Creation Cost (₹) | E4: Lowest Price (₹) | F4: Highest Price (₹) | G4: Avg Selling Price (₹) | H4: Total Cost to Build All (₹) | I4: Avg Units for ₹2L | J4: Avg Units for ₹10L
A5: 1 | B5: Templates & Spreadsheets | C5: =COUNTIF('Product Ideas'!$B$2:$B$217,B5) | D5: =AVERAGEIF('Product Ideas'!$B$2:$B$217,B5,'Product Ideas'!$G$2:$G$217) | E5: =_xlfn.MINIFS('Product Ideas'!$H$2:$H$217,'Product Ideas'!$B$2:$B$217,B5) | F5: =_xlfn.MAXIFS('Product Ideas'!$H$2:$H$217,'Product Ideas'!$B$2:$B$217,B5) | G5: =AVERAGEIF('Product Ideas'!$B$2:$B$217,B5,'Product Ideas'!$H$2:$H$217) | H5: =SUMIF('Product Ideas'!$B$2:$B$217,B5,'Product Ideas'!$G$2:$G$217) | I5: =AVERAGEIF('Product Ideas'!$B$2:$B$217,B5,'Product Ideas'!$K$2:$K$217) | J5: =AVERAGEIF('Product Ideas'!$B$2:$B$217,B5,'Product Ideas'!$L$2:$L$217)
A6: 2 | B6: Business & Corporate Toolkits | C6: =COUNTIF('Product Ideas'!$B$2:$B$217,B6) | D6: =AVERAGEIF('Product Ideas'!$B$2:$B$217,B6,'Product Ideas'!$G$2:$G$217) | E6: =_xlfn.MINIFS('Product Ideas'!$H$2:$H$217,'Product Ideas'!$B$2:$B$217,B6) | F6: =_xlfn.MAXIFS('Product Ideas'!$H$2:$H$217,'Product Ideas'!$B$2:$B$217,B6) | G6: =AVERAGEIF('Product Ideas'!$B$2:$B$217,B6,'Product Ideas'!$H$2:$H$217) | H6: =SUMIF('Product Ideas'!$B$2:$B$217,B6,'Product Ideas'!$G$2:$G$217) | I6: =AVERAGEIF('Product Ideas'!$B$2:$B$217,B6,'Product Ideas'!$K$2:$K$217) | J6: =AVERAGEIF('Product Ideas'!$B$2:$B$217,B6,'Product Ideas'!$L$2:$L$217)
A7: 3 | B7: Online Courses & Workshops | C7: =COUNTIF('Product Ideas'!$B$2:$B$217,B7) | D7: =AVERAGEIF('Product Ideas'!$B$2:$B$217,B7,'Product Ideas'!$G$2:$G$217) | E7: =_xlfn.MINIFS('Product Ideas'!$H$2:$H$217,'Product Ideas'!$B$2:$B$217,B7) | F7: =_xlfn.MAXIFS('Product Ideas'!$H$2:$H$217,'Product Ideas'!$B$2:$B$217,B7) | G7: =AVERAGEIF('Product Ideas'!$B$2:$B$217,B7,'Product Ideas'!$H$2:$H$217) | H7: =SUMIF('Product Ideas'!$B$2:$B$217,B7,'Product Ideas'!$G$2:$G$217) | I7: =AVERAGEIF('Product Ideas'!$B$2:$B$217,B7,'Product Ideas'!$K$2:$K$217) | J7: =AVERAGEIF('Product Ideas'!$B$2:$B$217,B7,'Product Ideas'!$L$2:$L$217)
A8: 4 | B8: eBooks & Guides | C8: =COUNTIF('Product Ideas'!$B$2:$B$217,B8) | D8: =AVERAGEIF('Product Ideas'!$B$2:$B$217,B8,'Product Ideas'!$G$2:$G$217) | E8: =_xlfn.MINIFS('Product Ideas'!$H$2:$H$217,'Product Ideas'!$B$2:$B$217,B8) | F8: =_xlfn.MAXIFS('Product Ideas'!$H$2:$H$217,'Product Ideas'!$B$2:$B$217,B8) | G8: =AVERAGEIF('Product Ideas'!$B$2:$B$217,B8,'Product Ideas'!$H$2:$H$217) | H8: =SUMIF('Product Ideas'!$B$2:$B$217,B8,'Product Ideas'!$G$2:$G$217) | I8: =AVERAGEIF('Product Ideas'!$B$2:$B$217,B8,'Product Ideas'!$K$2:$K$217) | J8: =AVERAGEIF('Product Ideas'!$B$2:$B$217,B8,'Product Ideas'!$L$2:$L$217)
A9: 5 | B9: Software, SaaS Micro-tools & Apps | C9: =COUNTIF('Product Ideas'!$B$2:$B$217,B9) | D9: =AVERAGEIF('Product Ideas'!$B$2:$B$217,B9,'Product Ideas'!$G$2:$G$217) | E9: =_xlfn.MINIFS('Product Ideas'!$H$2:$H$217,'Product Ideas'!$B$2:$B$217,B9) | F9: =_xlfn.MAXIFS('Product Ideas'!$H$2:$H$217,'Product Ideas'!$B$2:$B$217,B9) | G9: =AVERAGEIF('Product Ideas'!$B$2:$B$217,B9,'Product Ideas'!$H$2:$H$217) | H9: =SUMIF('Product Ideas'!$B$2:$B$217,B9,'Product Ideas'!$G$2:$G$217) | I9: =AVERAGEIF('Product Ideas'!$B$2:$B$217,B9,'Product Ideas'!$K$2:$K$217) | J9: =AVERAGEIF('Product Ideas'!$B$2:$B$217,B9,'Product Ideas'!$L$2:$L$217)
A10: 6 | B10: AI Prompts, GPTs & Automation | C10: =COUNTIF('Product Ideas'!$B$2:$B$217,B10) | D10: =AVERAGEIF('Product Ideas'!$B$2:$B$217,B10,'Product Ideas'!$G$2:$G$217) | E10: =_xlfn.MINIFS('Product Ideas'!$H$2:$H$217,'Product Ideas'!$B$2:$B$217,B10) | F10: =_xlfn.MAXIFS('Product Ideas'!$H$2:$H$217,'Product Ideas'!$B$2:$B$217,B10) | G10: =AVERAGEIF('Product Ideas'!$B$2:$B$217,B10,'Product Ideas'!$H$2:$H$217) | H10: =SUMIF('Product Ideas'!$B$2:$B$217,B10,'Product Ideas'!$G$2:$G$217) | I10: =AVERAGEIF('Product Ideas'!$B$2:$B$217,B10,'Product Ideas'!$K$2:$K$217) | J10: =AVERAGEIF('Product Ideas'!$B$2:$B$217,B10,'Product Ideas'!$L$2:$L$217)
A11: 7 | B11: Design Assets & Graphics | C11: =COUNTIF('Product Ideas'!$B$2:$B$217,B11) | D11: =AVERAGEIF('Product Ideas'!$B$2:$B$217,B11,'Product Ideas'!$G$2:$G$217) | E11: =_xlfn.MINIFS('Product Ideas'!$H$2:$H$217,'Product Ideas'!$B$2:$B$217,B11) | F11: =_xlfn.MAXIFS('Product Ideas'!$H$2:$H$217,'Product Ideas'!$B$2:$B$217,B11) | G11: =AVERAGEIF('Product Ideas'!$B$2:$B$217,B11,'Product Ideas'!$H$2:$H$217) | H11: =SUMIF('Product Ideas'!$B$2:$B$217,B11,'Product Ideas'!$G$2:$G$217) | I11: =AVERAGEIF('Product Ideas'!$B$2:$B$217,B11,'Product Ideas'!$K$2:$K$217) | J11: =AVERAGEIF('Product Ideas'!$B$2:$B$217,B11,'Product Ideas'!$L$2:$L$217)
A12: 8 | B12: Marketing & Social Media Kits | C12: =COUNTIF('Product Ideas'!$B$2:$B$217,B12) | D12: =AVERAGEIF('Product Ideas'!$B$2:$B$217,B12,'Product Ideas'!$G$2:$G$217) | E12: =_xlfn.MINIFS('Product Ideas'!$H$2:$H$217,'Product Ideas'!$B$2:$B$217,B12) | F12: =_xlfn.MAXIFS('Product Ideas'!$H$2:$H$217,'Product Ideas'!$B$2:$B$217,B12) | G12: =AVERAGEIF('Product Ideas'!$B$2:$B$217,B12,'Product Ideas'!$H$2:$H$217) | H12: =SUMIF('Product Ideas'!$B$2:$B$217,B12,'Product Ideas'!$G$2:$G$217) | I12: =AVERAGEIF('Product Ideas'!$B$2:$B$217,B12,'Product Ideas'!$K$2:$K$217) | J12: =AVERAGEIF('Product Ideas'!$B$2:$B$217,B12,'Product Ideas'!$L$2:$L$217)
A13: 9 | B13: Education & Exam Prep | C13: =COUNTIF('Product Ideas'!$B$2:$B$217,B13) | D13: =AVERAGEIF('Product Ideas'!$B$2:$B$217,B13,'Product Ideas'!$G$2:$G$217) | E13: =_xlfn.MINIFS('Product Ideas'!$H$2:$H$217,'Product Ideas'!$B$2:$B$217,B13) | F13: =_xlfn.MAXIFS('Product Ideas'!$H$2:$H$217,'Product Ideas'!$B$2:$B$217,B13) | G13: =AVERAGEIF('Product Ideas'!$B$2:$B$217,B13,'Product Ideas'!$H$2:$H$217) | H13: =SUMIF('Product Ideas'!$B$2:$B$217,B13,'Product Ideas'!$G$2:$G$217) | I13: =AVERAGEIF('Product Ideas'!$B$2:$B$217,B13,'Product Ideas'!$K$2:$K$217) | J13: =AVERAGEIF('Product Ideas'!$B$2:$B$217,B13,'Product Ideas'!$L$2:$L$217)
A14: 10 | B14: Finance, Investing & Tax | C14: =COUNTIF('Product Ideas'!$B$2:$B$217,B14) | D14: =AVERAGEIF('Product Ideas'!$B$2:$B$217,B14,'Product Ideas'!$G$2:$G$217) | E14: =_xlfn.MINIFS('Product Ideas'!$H$2:$H$217,'Product Ideas'!$B$2:$B$217,B14) | F14: =_xlfn.MAXIFS('Product Ideas'!$H$2:$H$217,'Product Ideas'!$B$2:$B$217,B14) | G14: =AVERAGEIF('Product Ideas'!$B$2:$B$217,B14,'Product Ideas'!$H$2:$H$217) | H14: =SUMIF('Product Ideas'!$B$2:$B$217,B14,'Product Ideas'!$G$2:$G$217) | I14: =AVERAGEIF('Product Ideas'!$B$2:$B$217,B14,'Product Ideas'!$K$2:$K$217) | J14: =AVERAGEIF('Product Ideas'!$B$2:$B$217,B14,'Product Ideas'!$L$2:$L$217)
A15: 11 | B15: Health, Fitness & Lifestyle | C15: =COUNTIF('Product Ideas'!$B$2:$B$217,B15) | D15: =AVERAGEIF('Product Ideas'!$B$2:$B$217,B15,'Product Ideas'!$G$2:$G$217) | E15: =_xlfn.MINIFS('Product Ideas'!$H$2:$H$217,'Product Ideas'!$B$2:$B$217,B15) | F15: =_xlfn.MAXIFS('Product Ideas'!$H$2:$H$217,'Product Ideas'!$B$2:$B$217,B15) | G15: =AVERAGEIF('Product Ideas'!$B$2:$B$217,B15,'Product Ideas'!$H$2:$H$217) | H15: =SUMIF('Product Ideas'!$B$2:$B$217,B15,'Product Ideas'!$G$2:$G$217) | I15: =AVERAGEIF('Product Ideas'!$B$2:$B$217,B15,'Product Ideas'!$K$2:$K$217) | J15: =AVERAGEIF('Product Ideas'!$B$2:$B$217,B15,'Product Ideas'!$L$2:$L$217)
A16: 12 | B16: Creative Media: Audio, Video, Photo & Stock | C16: =COUNTIF('Product Ideas'!$B$2:$B$217,B16) | D16: =AVERAGEIF('Product Ideas'!$B$2:$B$217,B16,'Product Ideas'!$G$2:$G$217) | E16: =_xlfn.MINIFS('Product Ideas'!$H$2:$H$217,'Product Ideas'!$B$2:$B$217,B16) | F16: =_xlfn.MAXIFS('Product Ideas'!$H$2:$H$217,'Product Ideas'!$B$2:$B$217,B16) | G16: =AVERAGEIF('Product Ideas'!$B$2:$B$217,B16,'Product Ideas'!$H$2:$H$217) | H16: =SUMIF('Product Ideas'!$B$2:$B$217,B16,'Product Ideas'!$G$2:$G$217) | I16: =AVERAGEIF('Product Ideas'!$B$2:$B$217,B16,'Product Ideas'!$K$2:$K$217) | J16: =AVERAGEIF('Product Ideas'!$B$2:$B$217,B16,'Product Ideas'!$L$2:$L$217)
B17: TOTAL / OVERALL | C17: =SUM(C5:C16) | D17: =AVERAGE('Product Ideas'!$G$2:$G$217) | E17: =MIN('Product Ideas'!$H$2:$H$217) | F17: =MAX('Product Ideas'!$H$2:$H$217) | G17: =AVERAGE('Product Ideas'!$H$2:$H$217) | H17: =SUM(H5:H16) | I17: =AVERAGE('Product Ideas'!$K$2:$K$217) | J17: =AVERAGE('Product Ideas'!$L$2:$L$217)
B20: Example: a 3-product plan to reach ₹2 lakh (edit the blue cells)
B21: Product (type an ID from Product Ideas) | C21: Product ID | D21: Price (₹) | E21: Units Sold | F21: Revenue (₹)
B22: =INDEX('Product Ideas'!$C$2:$C$217,MATCH(C22,'Product Ideas'!$A$2:$A$217,0)) | C22: 1 | D22: =INDEX('Product Ideas'!$H$2:$H$217,MATCH(C22,'Product Ideas'!$A$2:$A$217,0)) | E22: 150 | F22: =D22*E22
B23: =INDEX('Product Ideas'!$C$2:$C$217,MATCH(C23,'Product Ideas'!$A$2:$A$217,0)) | C23: 4 | D23: =INDEX('Product Ideas'!$H$2:$H$217,MATCH(C23,'Product Ideas'!$A$2:$A$217,0)) | E23: 50 | F23: =D23*E23
B24: =INDEX('Product Ideas'!$C$2:$C$217,MATCH(C24,'Product Ideas'!$A$2:$A$217,0)) | C24: 23 | D24: =INDEX('Product Ideas'!$H$2:$H$217,MATCH(C24,'Product Ideas'!$A$2:$A$217,0)) | E24: 25 | F24: =D24*E24
B25: Total revenue | F25: =SUM(F22:F24)
B26: Progress vs ₹2L target | F26: =IF(Assumptions!$B$4>0,F25/Assumptions!$B$4,0)
B27: Progress vs ₹10L target | F27: =IF(Assumptions!$B$5>0,F25/Assumptions!$B$5,0)
B28: Ad spend for 3 months (Assumptions) | F28: =Assumptions!$B$7*3
B29: Revenue after fees and 3 months of ads | F29: =F25*(1-Assumptions!$B$6)-F28

Sheet Assumptions
A1: Digital Product System - Assumptions & How to Use
A3: Input | B3: Value | C3: Note
A4: Revenue target - low (₹) | B4: 200000 | C4: The ₹2 lakh revenue goal you gave
A5: Revenue target - high (₹) | B5: 1000000 | C5: The ₹10 lakh revenue goal you gave
A6: Payment gateway + platform fees (% of price) | B6: 0.05 | C6: Assumption: Razorpay/Cosmofeed/Instamojo charge about 2-3% plus GST, and marketplaces take more. 5% is a safe average. Etsy/Udemy/app stores take 15-50%, so raise this if you sell mainly there.
A7: Monthly ad budget per product (₹) - optional | B7: 10000 | C7: Assumption: a starting Meta/Google ad budget. Only used on the Summary sheet.
A10: HOW TO USE THIS SHEET
A11: 1. Yellow cells with blue text are inputs you can change. Everything else updates on its own.
A12: 2. On 'Product Ideas', Creation Cost and Selling Price (blue) are my starting estimates. Change them to your own real quotes and prices.
A13: 3. Creation Cost = one-time money you spend to make version 1: tools (Canva Pro ~₹500/mo, ChatGPT/Claude ~₹2,000/mo), freelancers, expert/lawyer review, and a basic mic/camera for video. Your own time is not counted.
A14: 4. For subscription or licence items, 'Units' means paid subscriber-months or licences sold. Example: 100 subscribers x 12 months = 1,200 units.
A15: 5. Filter the Product Ideas sheet by Segment, Pricing Model or Target Audience to shortlist ideas.
A16: 6. Suggested path to ₹2-10 lakh: pick 1 segment you know, launch 3 products (a low-priced entry product, a mid-priced core product and a premium one), then bundle them.
A17: 7. Compliance: stock-market content must be education only (SEBI rules). Health/diet products need review by a qualified expert. Legal templates need a lawyer's review. Register for GST once turnover crosses ₹20 lakh (₹10 lakh in special-category states) or when selling through marketplaces that require it.
A18: 8. Prices are for the Indian market in 2026 and are indicative. Validate each one with a pre-sale or waitlist before building.

Sheet Product Ideas
A1: ID | B1: Segment | C1: Digital Product Idea | D1: Detailed Explanation (what it is & why it sells) | E1: Target Audience | F1: Pricing Model | G1: Creation Cost (₹, one-time) | H1: Selling Price (₹ per unit) | I1: Net per Sale after Fees (₹) | J1: Break-even Units | K1: Units Needed for ₹2L Revenue | L1: Units Needed for ₹10L Revenue | M1: Profit at ₹2L Revenue (₹) | N1: Profit at ₹10L Revenue (₹) | O1: Tools to Build It | P1: Where to Sell
A2: 1 | B2: Templates & Spreadsheets | C2: GST Invoice & Billing Excel Template | D2: Auto-calculates CGST/SGST/IGST, numbers invoices, keeps a customer ledger. Every GST-registered small seller needs clean invoices without paying for software. | E2: Small traders, freelancers, MSMEs | F2: One-time | G2: 3000 | H2: 499 | I2: =H2*(1-Assumptions!$B$6) | J2: =IF(I2>0,CEILING(G2/I2,1),0) | K2: =IF(H2>0,CEILING(Assumptions!$B$4/H2,1),0) | L2: =IF(H2>0,CEILING(Assumptions!$B$5/H2,1),0) | M2: =Assumptions!$B$4*(1-Assumptions!$B$6)-G2 | N2: =Assumptions!$B$5*(1-Assumptions!$B$6)-G2 | O2: Excel, Google Sheets, Notion, ChatGPT/Claude for formulas | P2: Own website (Razorpay/Cosmofeed/Gumroad), Etsy, Instagram, WhatsApp groups
A3: 2 | B3: Templates & Spreadsheets | C3: Small Business Accounting Dashboard (Google Sheets) | D3: P&L, cash-flow, expense categories and monthly charts in one sheet. Gives owners a CFO-style view without hiring an accountant. | E3: Shop owners, early-stage founders | F3: One-time | G3: 5000 | H3: 999 | I3: =H3*(1-Assumptions!$B$6) | J3: =IF(I3>0,CEILING(G3/I3,1),0) | K3: =IF(H3>0,CEILING(Assumptions!$B$4/H3,1),0) | L3: =IF(H3>0,CEILING(Assumptions!$B$5/H3,1),0) | M3: =Assumptions!$B$4*(1-Assumptions!$B$6)-G3 | N3: =Assumptions!$B$5*(1-Assumptions!$B$6)-G3 | O3: Excel, Google Sheets, Notion, ChatGPT/Claude for formulas | P3: Own website (Razorpay/Cosmofeed/Gumroad), Etsy, Instagram, WhatsApp groups
A4: 3 | B4: Templates & Spreadsheets | C4: Inventory & Stock Management Sheet | D4: SKU tracking, reorder-level alerts, supplier list and stock valuation. Stops over-stocking and stock-outs. | E4: Retailers, D2C sellers, distributors | F4: One-time | G4: 4000 | H4: 799 | I4: =H4*(1-Assumptions!$B$6) | J4: =IF(I4>0,CEILING(G4/I4,1),0) | K4: =IF(H4>0,CEILING(Assumptions!$B$4/H4,1),0) | L4: =IF(H4>0,CEILING(Assumptions!$B$5/H4,1),0) | M4: =Assumptions!$B$4*(1-Assumptions!$B$6)-G4 | N4: =Assumptions!$B$5*(1-Assumptions!$B$6)-G4 | O4: Excel, Google Sheets, Notion, ChatGPT/Claude for formulas | P4: Own website (Razorpay/Cosmofeed/Gumroad), Etsy, Instagram, WhatsApp groups
A5: 4 | B5: Templates & Spreadsheets | C5: Notion Business Operating System | D5: Tasks, clients, content, finances and SOPs linked in one Notion workspace. Sells well to people who want to 'run the business from one place'. | E5: Solopreneurs, creators, agency owners | F5: One-time | G5: 5000 | H5: 1499 | I5: =H5*(1-Assumptions!$B$6) | J5: =IF(I5>0,CEILING(G5/I5,1),0) | K5: =IF(H5>0,CEILING(Assumptions!$B$4/H5,1),0) | L5: =IF(H5>0,CEILING(Assumptions!$B$5/H5,1),0) | M5: =Assumptions!$B$4*(1-Assumptions!$B$6)-G5 | N5: =Assumptions!$B$5*(1-Assumptions!$B$6)-G5 | O5: Excel, Google Sheets, Notion, ChatGPT/Claude for formulas | P5: Own website (Razorpay/Cosmofeed/Gumroad), Etsy, Instagram, WhatsApp groups
A6: 5 | B6: Templates & Spreadsheets | C6: Personal Budget & Expense Tracker | D6: Monthly budget, category-wise spending, savings goals and yearly summary with charts. | E6: Salaried professionals, young couples | F6: One-time | G6: 2000 | H6: 299 | I6: =H6*(1-Assumptions!$B$6) | J6: =IF(I6>0,CEILING(G6/I6,1),0) | K6: =IF(H6>0,CEILING(Assumptions!$B$4/H6,1),0) | L6: =IF(H6>0,CEILING(Assumptions!$B$5/H6,1),0) | M6: =Assumptions!$B$4*(1-Assumptions!$B$6)-G6 | N6: =Assumptions!$B$5*(1-Assumptions!$B$6)-G6 | O6: Excel, Google Sheets, Notion, ChatGPT/Claude for formulas | P6: Own website (Razorpay/Cosmofeed/Gumroad), Etsy, Instagram, WhatsApp groups
A7: 6 | B7: Templates & Spreadsheets | C7: Project Management Tracker with Gantt Chart | D7: Tasks, owners, deadlines and an auto-drawn Gantt timeline. Cheaper than paid PM tools for small teams. | E7: Project managers, agencies, IT teams | F7: One-time | G7: 3000 | H7: 699 | I7: =H7*(1-Assumptions!$B$6) | J7: =IF(I7>0,CEILING(G7/I7,1),0) | K7: =IF(H7>0,CEILING(Assumptions!$B$4/H7,1),0) | L7: =IF(H7>0,CEILING(Assumptions!$B$5/H7,1),0) | M7: =Assumptions!$B$4*(1-Assumptions!$B$6)-G7 | N7: =Assumptions!$B$5*(1-Assumptions!$B$6)-G7 | O7: Excel, Google Sheets, Notion, ChatGPT/Claude for formulas | P7: Own website (Razorpay/Cosmofeed/Gumroad), Etsy, Instagram, WhatsApp groups
A8: 7 | B8: Templates & Spreadsheets | C8: Sales CRM in Google Sheets | D8: Lead pipeline, follow-up reminders, deal stages and conversion reports. An easy first CRM for teams not ready for Salesforce/Zoho. | E8: Sales teams, real-estate & insurance agents | F8: One-time | G8: 4000 | H8: 999 | I8: =H8*(1-Assumptions!$B$6) | J8: =IF(I8>0,CEILING(G8/I8,1),0) | K8: =IF(H8>0,CEILING(Assumptions!$B$4/H8,1),0) | L8: =IF(H8>0,CEILING(Assumptions!$B$5/H8,1),0) | M8: =Assumptions!$B$4*(1-Assumptions!$B$6)-G8 | N8: =Assumptions!$B$5*(1-Assumptions!$B$6)-G8 | O8: Excel, Google Sheets, Notion, ChatGPT/Claude for formulas | P8: Own website (Razorpay/Cosmofeed/Gumroad), Etsy, Instagram, WhatsApp groups
A9: 8 | B9: Templates & Spreadsheets | C9: Payroll & Salary Slip Generator (PF/ESI/TDS) | D9: Calculates gross-to-net salary with PF, ESI, PT and TDS and prints salary slips in bulk. | E9: HR/admin at SMEs with 5-100 staff | F9: One-time | G9: 6000 | H9: 1499 | I9: =H9*(1-Assumptions!$B$6) | J9: =IF(I9>0,CEILING(G9/I9,1),0) | K9: =IF(H9>0,CEILING(Assumptions!$B$4/H9,1),0) | L9: =IF(H9>0,CEILING(Assumptions!$B$5/H9,1),0) | M9: =Assumptions!$B$4*(1-Assumptions!$B$6)-G9 | N9: =Assumptions!$B$5*(1-Assumptions!$B$6)-G9 | O9: Excel, Google Sheets, Notion, ChatGPT/Claude for formulas | P9: Own website (Razorpay/Cosmofeed/Gumroad), Etsy, Instagram, WhatsApp groups
A10: 9 | B10: Templates & Spreadsheets | C10: Employee Attendance & Leave Tracker | D10: Daily attendance, leave balances, holidays and a monthly summary per employee. | E10: HR managers, schools, factories | F10: One-time | G10: 3000 | H10: 599 | I10: =H10*(1-Assumptions!$B$6) | J10: =IF(I10>0,CEILING(G10/I10,1),0) | K10: =IF(H10>0,CEILING(Assumptions!$B$4/H10,1),0) | L10: =IF(H10>0,CEILING(Assumptions!$B$5/H10,1),0) | M10: =Assumptions!$B$4*(1-Assumptions!$B$6)-G10 | N10: =Assumptions!$B$5*(1-Assumptions!$B$6)-G10 | O10: Excel, Google Sheets, Notion, ChatGPT/Claude for formulas | P10: Own website (Razorpay/Cosmofeed/Gumroad), Etsy, Instagram, WhatsApp groups
A11: 10 | B11: Templates & Spreadsheets | C11: Social Media Content Calendar | D11: Plan posts by platform, date, format and status, with a hashtag bank and monthly analytics tab. | E11: Social media managers, creators | F11: One-time | G11: 2000 | H11: 399 | I11: =H11*(1-Assumptions!$B$6) | J11: =IF(I11>0,CEILING(G11/I11,1),0) | K11: =IF(H11>0,CEILING(Assumptions!$B$4/H11,1),0) | L11: =IF(H11>0,CEILING(Assumptions!$B$5/H11,1),0) | M11: =Assumptions!$B$4*(1-Assumptions!$B$6)-G11 | N11: =Assumptions!$B$5*(1-Assumptions!$B$6)-G11 | O11: Excel, Google Sheets, Notion, ChatGPT/Claude for formulas | P11: Own website (Razorpay/Cosmofeed/Gumroad), Etsy, Instagram, WhatsApp groups
A12: 11 | B12: Templates & Spreadsheets | C12: Wedding Planner & Budget Template | D12: Guest list, vendor tracker, budget vs actual, and a day-wise function checklist for Indian weddings. | E12: Engaged couples, wedding planners | F12: One-time | G12: 2500 | H12: 499 | I12: =H12*(1-Assumptions!$B$6) | J12: =IF(I12>0,CEILING(G12/I12,1),0) | K12: =IF(H12>0,CEILING(Assumptions!$B$4/H12,1),0) | L12: =IF(H12>0,CEILING(Assumptions!$B$5/H12,1),0) | M12: =Assumptions!$B$4*(1-Assumptions!$B$6)-G12 | N12: =Assumptions!$B$5*(1-Assumptions!$B$6)-G12 | O12: Excel, Google Sheets, Notion, ChatGPT/Claude for formulas | P12: Own website (Razorpay/Cosmofeed/Gumroad), Etsy, Instagram, WhatsApp groups
A13: 12 | B13: Templates & Spreadsheets | C13: Restaurant Food Costing & Menu Pricing Sheet | D13: Recipe-wise cost, plate cost %, and suggested menu price. Restaurants often lose margin without this. | E13: Restaurant & cloud-kitchen owners | F13: One-time | G13: 4000 | H13: 999 | I13: =H13*(1-Assumptions!$B$6) | J13: =IF(I13>0,CEILING(G13/I13,1),0) | K13: =IF(H13>0,CEILING(Assumptions!$B$4/H13,1),0) | L13: =IF(H13>0,CEILING(Assumptions!$B$5/H13,1),0) | M13: =Assumptions!$B$4*(1-Assumptions!$B$6)-G13 | N13: =Assumptions!$B$5*(1-Assumptions!$B$6)-G13 | O13: Excel, Google Sheets, Notion, ChatGPT/Claude for formulas | P13: Own website (Razorpay/Cosmofeed/Gumroad), Etsy, Instagram, WhatsApp groups
... A217: 216 | B217: Creative Media: Audio, Video, Photo & Stock | C217: Corporate Event Video Template Pack | D217: Annual-day, awards and launch-event video templates. | E217: Corporate comms & event agencies | F217: One-time | G217: 8000 | H217: 1999 | I217: =H217*(1-Assumptions!$B$6) | J217: =IF(I217>0,CEILING(G217/I217,1),0) | K217: =IF(H217>0,CEILING(Assumptions!$B$4/H217,1),0) | L217: =IF(H217>0,CEILING(Assumptions!$B$5/H217,1),0) | M217: =Assumptions!$B$4*(1-Assumptions!$B$6)-G217 | N217: =Assumptions!$B$5*(1-Assumptions!$B$6)-G217 | O217: Camera/phone, Lightroom, Premiere/After Effects/CapCut, DAW (FL Studio/Audacity), Blender | P217: Own website, Envato/Adobe Stock/Shutterstock, Etsy, Instagram, YouTube
